{
    "name": "exp4_3800_0",
    "best_structure": {
        "polygons": [
            {
                "id": "tmp",
                "points": [
                    {
                        "_x": 466.0,
                        "_y": 0.0,
                        "_z": 0.0,
                        "_class_path": "gefest.core.structure.point/Point"
                    },
                    {
                        "_x": 12.0,
                        "_y": 4.0,
                        "_z": 0.0,
                        "_class_path": "gefest.core.structure.point/Point"
                    },
                    {
                        "_x": 29.0,
                        "_y": 206.0,
                        "_z": 0.0,
                        "_class_path": "gefest.core.structure.point/Point"
                    },
                    {
                        "_x": 68.0,
                        "_y": 599.0,
                        "_z": 0.0,
                        "_class_path": "gefest.core.structure.point/Point"
                    },
                    {
                        "_x": 359.0,
                        "_y": 727.0,
                        "_z": 0.0,
                        "_class_path": "gefest.core.structure.point/Point"
                    },
                    {
                        "_x": 445.0,
                        "_y": 708.0,
                        "_z": 0.0,
                        "_class_path": "gefest.core.structure.point/Point"
                    },
                    {
                        "_x": 676.0,
                        "_y": 589.0,
                        "_z": 0.0,
                        "_class_path": "gefest.core.structure.point/Point"
                    },
                    {
                        "_x": 795.0,
                        "_y": 349.0,
                        "_z": 0.0,
                        "_class_path": "gefest.core.structure.point/Point"
                    },
                    {
                        "_x": 771.0,
                        "_y": 168.0,
                        "_z": 0.0,
                        "_class_path": "gefest.core.structure.point/Point"
                    },
                    {
                        "_x": 587.0,
                        "_y": 39.0,
                        "_z": 0.0,
                        "_class_path": "gefest.core.structure.point/Point"
                    },
                    {
                        "_x": 466.0,
                        "_y": 0.0,
                        "_z": 0.0,
                        "_class_path": "gefest.core.structure.point/Point"
                    }
                ],
                "_class_path": "gefest.core.structure.polygon/Polygon"
            }
        ],
        "_class_path": "gefest.core.structure.structure/Structure"
    },
    "fitness": 11.815632679145995,
    "metadata": {
        "max_gens": 100,
        "pop_size": 100,
        "time": 77.8472526000005
    },
    "_class_path": "gefest.core.opt.result/Result"
}