{
    "name": "exp4_3300_3",
    "best_structure": {
        "polygons": [
            {
                "id": "tmp",
                "points": [
                    {
                        "_x": 16.0,
                        "_y": 32.0,
                        "_z": 0.0,
                        "_class_path": "gefest.core.structure.point/Point"
                    },
                    {
                        "_x": 73.0,
                        "_y": 1367.0,
                        "_z": 0.0,
                        "_class_path": "gefest.core.structure.point/Point"
                    },
                    {
                        "_x": 713,
                        "_y": 386,
                        "_z": 0.0,
                        "_class_path": "gefest.core.structure.point/Point"
                    },
                    {
                        "_x": 25,
                        "_y": 12,
                        "_z": 0.0,
                        "_class_path": "gefest.core.structure.point/Point"
                    },
                    {
                        "_x": 16.0,
                        "_y": 32.0,
                        "_z": 0.0,
                        "_class_path": "gefest.core.structure.point/Point"
                    }
                ],
                "_class_path": "gefest.core.structure.polygon/Polygon"
            }
        ],
        "_class_path": "gefest.core.structure.structure/Structure"
    },
    "fitness": 27.301753905919266,
    "metadata": {
        "max_gens": 100,
        "pop_size": 100,
        "time": 75.1778020999991
    },
    "_class_path": "gefest.core.opt.result/Result"
}