{
    "name": "exp4_1600_6",
    "best_structure": {
        "polygons": [
            {
                "id": "tmp",
                "points": [
                    {
                        "_x": 8.0,
                        "_y": 1.0,
                        "_z": 0.0,
                        "_class_path": "gefest.core.structure.point/Point"
                    },
                    {
                        "_x": 10.0,
                        "_y": 519.0,
                        "_z": 0.0,
                        "_class_path": "gefest.core.structure.point/Point"
                    },
                    {
                        "_x": 194.0,
                        "_y": 859.0,
                        "_z": 0.0,
                        "_class_path": "gefest.core.structure.point/Point"
                    },
                    {
                        "_x": 563,
                        "_y": 940,
                        "_z": 0.0,
                        "_class_path": "gefest.core.structure.point/Point"
                    },
                    {
                        "_x": 957.0,
                        "_y": 580.0,
                        "_z": 0.0,
                        "_class_path": "gefest.core.structure.point/Point"
                    },
                    {
                        "_x": 723,
                        "_y": 65,
                        "_z": 0.0,
                        "_class_path": "gefest.core.structure.point/Point"
                    },
                    {
                        "_x": 8.0,
                        "_y": 1.0,
                        "_z": 0.0,
                        "_class_path": "gefest.core.structure.point/Point"
                    }
                ],
                "_class_path": "gefest.core.structure.polygon/Polygon"
            }
        ],
        "_class_path": "gefest.core.structure.structure/Structure"
    },
    "fitness": 7.208347306948376,
    "metadata": {
        "max_gens": 100,
        "pop_size": 100,
        "time": 76.40202600000157
    },
    "_class_path": "gefest.core.opt.result/Result"
}