{
    "name": "exp4_2000_9",
    "best_structure": {
        "polygons": [
            {
                "id": "tmp",
                "points": [
                    {
                        "_x": 31.0,
                        "_y": 12.0,
                        "_z": 0.0,
                        "_class_path": "gefest.core.structure.point/Point"
                    },
                    {
                        "_x": 4.0,
                        "_y": 136.0,
                        "_z": 0.0,
                        "_class_path": "gefest.core.structure.point/Point"
                    },
                    {
                        "_x": 5.0,
                        "_y": 156.0,
                        "_z": 0.0,
                        "_class_path": "gefest.core.structure.point/Point"
                    },
                    {
                        "_x": 19.0,
                        "_y": 203.0,
                        "_z": 0.0,
                        "_class_path": "gefest.core.structure.point/Point"
                    },
                    {
                        "_x": 116.0,
                        "_y": 226.0,
                        "_z": 0.0,
                        "_class_path": "gefest.core.structure.point/Point"
                    },
                    {
                        "_x": 324.0,
                        "_y": 263.0,
                        "_z": 0.0,
                        "_class_path": "gefest.core.structure.point/Point"
                    },
                    {
                        "_x": 368,
                        "_y": 192,
                        "_z": 0.0,
                        "_class_path": "gefest.core.structure.point/Point"
                    },
                    {
                        "_x": 271.0,
                        "_y": 27.0,
                        "_z": 0.0,
                        "_class_path": "gefest.core.structure.point/Point"
                    },
                    {
                        "_x": 31.0,
                        "_y": 12.0,
                        "_z": 0.0,
                        "_class_path": "gefest.core.structure.point/Point"
                    }
                ],
                "_class_path": "gefest.core.structure.polygon/Polygon"
            }
        ],
        "_class_path": "gefest.core.structure.structure/Structure"
    },
    "fitness": 32.505024356964206,
    "metadata": {
        "max_gens": 100,
        "pop_size": 100,
        "time": 78.2494954
    },
    "_class_path": "gefest.core.opt.result/Result"
}