{
    "name": "exp2_14_1",
    "best_structure": {
        "polygons": [
            {
                "id": "tmp",
                "points": [
                    {
                        "_x": 75.35105963390004,
                        "_y": 36.90166739113778,
                        "_z": 0.0,
                        "_class_path": "gefest.core.structure.point/Point"
                    },
                    {
                        "_x": 29,
                        "_y": 71,
                        "_z": 0.0,
                        "_class_path": "gefest.core.structure.point/Point"
                    },
                    {
                        "_x": 14.517300192064113,
                        "_y": 117.17154787051086,
                        "_z": 0.0,
                        "_class_path": "gefest.core.structure.point/Point"
                    },
                    {
                        "_x": 24.559797633096906,
                        "_y": 165.794055468812,
                        "_z": 0.0,
                        "_class_path": "gefest.core.structure.point/Point"
                    },
                    {
                        "_x": 62.33568869890158,
                        "_y": 223.1262632946446,
                        "_z": 0.0,
                        "_class_path": "gefest.core.structure.point/Point"
                    },
                    {
                        "_x": 164.58782273416602,
                        "_y": 246.80116741766713,
                        "_z": 0.0,
                        "_class_path": "gefest.core.structure.point/Point"
                    },
                    {
                        "_x": 238.49310573149594,
                        "_y": 186.10512846054425,
                        "_z": 0.0,
                        "_class_path": "gefest.core.structure.point/Point"
                    },
                    {
                        "_x": 240.26337892209477,
                        "_y": 84.94255567381327,
                        "_z": 0.0,
                        "_class_path": "gefest.core.structure.point/Point"
                    },
                    {
                        "_x": 155.13088984950872,
                        "_y": 29.144174834347908,
                        "_z": 0.0,
                        "_class_path": "gefest.core.structure.point/Point"
                    },
                    {
                        "_x": 116.8542135184536,
                        "_y": 24.15458075790798,
                        "_z": 0.0,
                        "_class_path": "gefest.core.structure.point/Point"
                    },
                    {
                        "_x": 75.35105963390004,
                        "_y": 36.90166739113778,
                        "_z": 0.0,
                        "_class_path": "gefest.core.structure.point/Point"
                    }
                ],
                "_class_path": "gefest.core.structure.polygon/Polygon"
            }
        ],
        "_class_path": "gefest.core.structure.structure/Structure"
    },
    "fitness": 0.08534727904926798,
    "metadata": {
        "max_gens": 100,
        "pop_size": 100,
        "time": 369.44229020000057
    },
    "_class_path": "gefest.core.opt.result/Result"
}